analysis/__init__.py
analysis/cds.py
analysis/clustering.py
analysis/variants.py
apggr-1.0.1.dist-info/METADATA
apggr-1.0.1.dist-info/WHEEL
apggr-1.0.1.dist-info/entry_points.txt
apggr-1.0.1.dist-info/licenses/LICENSE
apggr-1.0.1.dist-info/RECORD
